{
  "company": "Rodriguez, Figueroa and Sanchez",
  "company_short": "AND SONS",
  "hq_city": "Lake Joyside",
  "exp_policy_id": "EXP-2824",
  "exp_form_code": "NHR-1409",
  "exp_limit_quarterly": 959,
  "exp_single_receipt_threshold": 135,
  "exp_submission_days": 25,
  "exp_approval_code": "MGR-4657",
  "exp_finance_email": "garzaanthony@robinson.org",
  "it_policy_id": "ITS-3286",
  "it_password_days": 43,
  "it_session_timeout_min": 60,
  "it_vpn_id": "VPN-2424",
  "it_incident_hours": 19,
  "it_hotline_ext": "7912",
  "it_mfa_grace_days": 1,
  "ob_checklist_id": "OBD-1488",
  "ob_form_code": "NHR-2535",
  "ob_equipment_form": "EQP-4582",
  "ob_probation_days": 60,
  "ob_buddy_days": 9,
  "ob_orientation_hours": 11,
  "ob_hr_contact": "Cristian Santos",
  "ob_hr_ext": "1434",
  "ben_plan_id": "BEN-4257",
  "ben_health_deductible": 2750,
  "ben_hsa_limit": 3050,
  "ben_dental_pct": 84,
  "ben_vision_allowance": 230,
  "ben_pto_hours_per_month": 8,
  "ben_enrollment_days": 42,
  "vac_policy_id": "VAC-5557",
  "vac_max_days": 10,
  "vac_carryover_days": 5,
  "vac_advance_days": 25,
  "vac_payout_pct": 54,
  "vac_blackout_month": "September",
  "vac_form": "VAC-6574",
  "coc_policy_id": "COC-5552",
  "coc_report_form": "ETH-3547",
  "coc_hotline_ext": "4527",
  "coc_investigation_days": 58,
  "coc_escalation_days": 8,
  "coc_compliance_officer": "Kevin Pacheco",
  "coc_review_months": 6,
  "prf_policy_id": "PRF-2519",
  "prf_review_months": 12,
  "prf_rating_max": 4,
  "prf_bonus_pct": 16,
  "prf_okr_quota": 5,
  "prf_self_review_days": 13,
  "prf_calibration_form": "CAL-1711",
  "trn_course_id": "TRN-8527",
  "trn_deadline_days": 64,
  "trn_cert_id": "CERT-3045",
  "trn_passing_score": 82,
  "trn_retake_days": 5,
  "trn_credit_hours": 5,
  "trn_lms_code": "LMS-6925",
  "pro_policy_id": "PRO-4150",
  "pro_po_threshold": 5000,
  "pro_vendor_days": 7,
  "pro_contract_days": 4,
  "pro_approval_code": "APR-4733",
  "pro_email": "blakeerik@peterson-moore.com",
  "pro_emergency_limit": 650,
  "rw_policy_id": "RWP-2307",
  "rw_days_per_week": 2,
  "rw_equipment_allowance": 350,
  "rw_monthly_stipend": 150,
  "rw_vpn_id": "VPN-5554",
  "rw_core_start": "9:00 AM",
  "rw_core_end": "5:00 PM",
  "rw_request_form": "RWF-6977"
}